ckks/__init__.py
ckks/ckks.py
ckks-1.0.1.dist-info/LICENSE
ckks-1.0.1.dist-info/METADATA
ckks-1.0.1.dist-info/WHEEL
ckks-1.0.1.dist-info/top_level.txt
ckks-1.0.1.dist-info/RECORD
