Metadata-Version: 2.1
Name: ckks
Version: 1.0.1
Summary: Cryptography scheme CKKS
Author: mmazz (Matias Mazzanti)
Author-email: <mazzantimatiass@gmail.com>
Keywords: python,fhe,ckks,cryptography
Classifier: Development Status :: 1 - Planning
Classifier: Intended Audience :: Developers
Classifier: Programming Language :: Python :: 3
Classifier: Operating System :: Unix
Classifier: Operating System :: MacOS :: MacOS X
Classifier: Operating System :: Microsoft :: Windows
License-File: LICENSE
Requires-Dist: numpy
Requires-Dist: mpmath
